hespi/__init__.py
hespi/data/authority.txt
hespi/data/family.txt
hespi/data/genus.txt
hespi/data/mk-lists.py
hespi/data/references.bib
hespi/data/species.txt
hespi/download.py
hespi/hespi.py
hespi/llm.py
hespi/main.py
hespi/ocr.py
hespi/report.py
hespi/templates/assets/css/bootstrap.hespi.min.css
hespi/templates/assets/css/hespi.css
hespi/templates/assets/css/hespi.min.css
hespi/templates/assets/img/favicon.svg
hespi/templates/assets/img/feather-image.svg
hespi/templates/assets/img/hespi-favicon.png
hespi/templates/assets/img/hespi-logo2.svg
hespi/templates/assets/js/bootstrap.min.js
hespi/templates/report-template.html
hespi/tools.py
hespi/util.py
hespi/yolo.py
hespi-0.6.1.dist-info/LICENSE
hespi-0.6.1.dist-info/METADATA
hespi-0.6.1.dist-info/WHEEL
hespi-0.6.1.dist-info/entry_points.txt
hespi-0.6.1.dist-info/RECORD
