Metadata-Version: 2.3
Name: hespi
Version: 0.6.1
Summary: HErbarium Specimen sheet PIpeline
License: Apache-2.0
Keywords: herbarium,object detection,OCR,HTR,specimen,handwritten text recognition
Author: Robert Turnbull
Author-email: robert.turnbull@unimelb.edu.au
Requires-Python: >=3.10,<3.12
Classifier: Intended Audience :: Science/Research
Classifier: License :: OSI Approved :: Apache Software License
Classifier: Programming Language :: Python :: 3
Classifier: Programming Language :: Python :: 3.10
Classifier: Programming Language :: Python :: 3.11
Classifier: Topic :: Scientific/Engineering :: Bio-Informatics
Classifier: Topic :: Scientific/Engineering :: Image Processing
Classifier: Topic :: Scientific/Engineering :: Image Recognition
Classifier: Topic :: Software Development :: Libraries :: Python Modules
Requires-Dist: appdirs (>=1.4.4)
Requires-Dist: drawyolo (>=0.1.2)
Requires-Dist: fastai (<2.8.0)
Requires-Dist: jinja2 (>=3.1.2)
Requires-Dist: langchain (>=0.2.0)
Requires-Dist: langchain-anthropic (>=0.1.23,<0.2.0)
Requires-Dist: langchain-openai (>=0.1.0)
Requires-Dist: pytesseract (>=0.3.10)
Requires-Dist: rich (>=10.16.1)
Requires-Dist: torch (>=2.6.0)
Requires-Dist: torchapp (>=0.2.0,<0.4.0)
Requires-Dist: transformers (>=4.21.3)
Requires-Dist: typer (>=0.4.0)
Requires-Dist: ultralytics (>=8.1.0)
Project-URL: Documentation, https://rbturnbull.github.io/hespi/
Project-URL: Homepage, https://rbturnbull.github.io/hespi/
Project-URL: Repository, https://github.com/rbturnbull/hespi
